[
    {
        "date": "2024-04-24",
        "list": [
            {
                "scene": "technical_consulting",
                "total": 100,
                "passed": 61,
                "failed": 39,
                "pass_rate": "61.00%",
                "list": [
                    {
                        "total": 20,
                        "passed": 11,
                        "failed": 9,
                        "pass_rate": "55.00%",
                        "source": "https://github.com/sparticleinc/ASEED/blob/main/evaluations/technical_consulting/20240424-perplexity.json",
                        "source_csv": "https://github.com/sparticleinc/ASEED/blob/main/evaluations/technical_consulting/20240424-perplexity.csv",
                        "evaluate_ai": "perplexity"
                    },
                    {
                        "total": 20,
                        "passed": 18,
                        "failed": 2,
                        "pass_rate": "90.00%",
                        "source": "https://github.com/sparticleinc/ASEED/blob/main/evaluations/technical_consulting/20240424-glarity_search.json",
                        "source_csv": "https://github.com/sparticleinc/ASEED/blob/main/evaluations/technical_consulting/20240424-glarity_search.csv",
                        "evaluate_ai": "glarity_search"
                    },
                    {
                        "total": 20,
                        "passed": 12,
                        "failed": 8,
                        "pass_rate": "60.00%",
                        "source": "https://github.com/sparticleinc/ASEED/blob/main/evaluations/technical_consulting/20240424-metaso.json",
                        "source_csv": "https://github.com/sparticleinc/ASEED/blob/main/evaluations/technical_consulting/20240424-metaso.csv",
                        "evaluate_ai": "metaso"
                    },
                    {
                        "total": 20,
                        "passed": 9,
                        "failed": 11,
                        "pass_rate": "45.00%",
                        "source": "https://github.com/sparticleinc/ASEED/blob/main/evaluations/technical_consulting/20240424-you.json",
                        "source_csv": "https://github.com/sparticleinc/ASEED/blob/main/evaluations/technical_consulting/20240424-you.csv",
                        "evaluate_ai": "you"
                    },
                    {
                        "total": 20,
                        "passed": 11,
                        "failed": 9,
                        "pass_rate": "55.00%",
                        "source": "https://github.com/sparticleinc/ASEED/blob/main/evaluations/technical_consulting/20240424-iask.json",
                        "source_csv": "https://github.com/sparticleinc/ASEED/blob/main/evaluations/technical_consulting/20240424-iask.csv",
                        "evaluate_ai": "iask"
                    }
                ]
            },
            {
                "scene": "real_time_news",
                "total": 100,
                "passed": 62,
                "failed": 38,
                "pass_rate": "62.00%",
                "list": [
                    {
                        "total": 20,
                        "passed": 13,
                        "failed": 7,
                        "pass_rate": "65.00%",
                        "source": "https://github.com/sparticleinc/ASEED/blob/main/evaluations/real_time_news/20240424-perplexity.json",
                        "source_csv": "https://github.com/sparticleinc/ASEED/blob/main/evaluations/real_time_news/20240424-perplexity.csv",
                        "evaluate_ai": "perplexity"
                    },
                    {
                        "total": 20,
                        "passed": 14,
                        "failed": 6,
                        "pass_rate": "70.00%",
                        "source": "https://github.com/sparticleinc/ASEED/blob/main/evaluations/real_time_news/20240424-glarity_search.json",
                        "source_csv": "https://github.com/sparticleinc/ASEED/blob/main/evaluations/real_time_news/20240424-glarity_search.csv",
                        "evaluate_ai": "glarity_search"
                    },
                    {
                        "total": 20,
                        "passed": 12,
                        "failed": 8,
                        "pass_rate": "60.00%",
                        "source": "https://github.com/sparticleinc/ASEED/blob/main/evaluations/real_time_news/20240424-metaso.json",
                        "source_csv": "https://github.com/sparticleinc/ASEED/blob/main/evaluations/real_time_news/20240424-metaso.csv",
                        "evaluate_ai": "metaso"
                    },
                    {
                        "total": 20,
                        "passed": 11,
                        "failed": 9,
                        "pass_rate": "55.00%",
                        "source": "https://github.com/sparticleinc/ASEED/blob/main/evaluations/real_time_news/20240424-you.json",
                        "source_csv": "https://github.com/sparticleinc/ASEED/blob/main/evaluations/real_time_news/20240424-you.csv",
                        "evaluate_ai": "you"
                    },
                    {
                        "total": 20,
                        "passed": 12,
                        "failed": 8,
                        "pass_rate": "60.00%",
                        "source": "https://github.com/sparticleinc/ASEED/blob/main/evaluations/real_time_news/20240424-iask.json",
                        "source_csv": "https://github.com/sparticleinc/ASEED/blob/main/evaluations/real_time_news/20240424-iask.csv",
                        "evaluate_ai": "iask"
                    }
                ]
            },
            {
                "scene": "local_search",
                "total": 100,
                "passed": 68,
                "failed": 32,
                "pass_rate": "68.00%",
                "list": [
                    {
                        "total": 20,
                        "passed": 16,
                        "failed": 4,
                        "pass_rate": "80.00%",
                        "source": "https://github.com/sparticleinc/ASEED/blob/main/evaluations/local_search/20240424-perplexity.json",
                        "source_csv": "https://github.com/sparticleinc/ASEED/blob/main/evaluations/local_search/20240424-perplexity.csv",
                        "evaluate_ai": "perplexity"
                    },
                    {
                        "total": 20,
                        "passed": 15,
                        "failed": 5,
                        "pass_rate": "75.00%",
                        "source": "https://github.com/sparticleinc/ASEED/blob/main/evaluations/local_search/20240424-glarity_search.json",
                        "source_csv": "https://github.com/sparticleinc/ASEED/blob/main/evaluations/local_search/20240424-glarity_search.csv",
                        "evaluate_ai": "glarity_search"
                    },
                    {
                        "total": 20,
                        "passed": 17,
                        "failed": 3,
                        "pass_rate": "85.00%",
                        "source": "https://github.com/sparticleinc/ASEED/blob/main/evaluations/local_search/20240424-metaso.json",
                        "source_csv": "https://github.com/sparticleinc/ASEED/blob/main/evaluations/local_search/20240424-metaso.csv",
                        "evaluate_ai": "metaso"
                    },
                    {
                        "total": 20,
                        "passed": 4,
                        "failed": 16,
                        "pass_rate": "20.00%",
                        "source": "https://github.com/sparticleinc/ASEED/blob/main/evaluations/local_search/20240424-you.json",
                        "source_csv": "https://github.com/sparticleinc/ASEED/blob/main/evaluations/local_search/20240424-you.csv",
                        "evaluate_ai": "you"
                    },
                    {
                        "total": 20,
                        "passed": 16,
                        "failed": 4,
                        "pass_rate": "80.00%",
                        "source": "https://github.com/sparticleinc/ASEED/blob/main/evaluations/local_search/20240424-iask.json",
                        "source_csv": "https://github.com/sparticleinc/ASEED/blob/main/evaluations/local_search/20240424-iask.csv",
                        "evaluate_ai": "iask"
                    }
                ]
            },
            {
                "scene": "products_search",
                "total": 100,
                "passed": 61,
                "failed": 39,
                "pass_rate": "61.00%",
                "list": [
                    {
                        "total": 20,
                        "passed": 13,
                        "failed": 7,
                        "pass_rate": "65.00%",
                        "source": "https://github.com/sparticleinc/ASEED/blob/main/evaluations/products_search/20240424-perplexity.json",
                        "source_csv": "https://github.com/sparticleinc/ASEED/blob/main/evaluations/products_search/20240424-perplexity.csv",
                        "evaluate_ai": "perplexity"
                    },
                    {
                        "total": 20,
                        "passed": 16,
                        "failed": 4,
                        "pass_rate": "80.00%",
                        "source": "https://github.com/sparticleinc/ASEED/blob/main/evaluations/products_search/20240424-glarity_search.json",
                        "source_csv": "https://github.com/sparticleinc/ASEED/blob/main/evaluations/products_search/20240424-glarity_search.csv",
                        "evaluate_ai": "glarity_search"
                    },
                    {
                        "total": 20,
                        "passed": 14,
                        "failed": 6,
                        "pass_rate": "70.00%",
                        "source": "https://github.com/sparticleinc/ASEED/blob/main/evaluations/products_search/20240424-metaso.json",
                        "source_csv": "https://github.com/sparticleinc/ASEED/blob/main/evaluations/products_search/20240424-metaso.csv",
                        "evaluate_ai": "metaso"
                    },
                    {
                        "total": 20,
                        "passed": 7,
                        "failed": 13,
                        "pass_rate": "35.00%",
                        "source": "https://github.com/sparticleinc/ASEED/blob/main/evaluations/products_search/20240424-you.json",
                        "source_csv": "https://github.com/sparticleinc/ASEED/blob/main/evaluations/products_search/20240424-you.csv",
                        "evaluate_ai": "you"
                    },
                    {
                        "total": 20,
                        "passed": 11,
                        "failed": 9,
                        "pass_rate": "55.00%",
                        "source": "https://github.com/sparticleinc/ASEED/blob/main/evaluations/products_search/20240424-iask.json",
                        "source_csv": "https://github.com/sparticleinc/ASEED/blob/main/evaluations/products_search/20240424-iask.csv",
                        "evaluate_ai": "iask"
                    }
                ]
            },
            {
                "scene": "business_consulting",
                "total": 100,
                "passed": 44,
                "failed": 56,
                "pass_rate": "44.00%",
                "answer_correctness": 0.6209667315825194,
                "list": [
                    {
                        "total": 20,
                        "passed": 12,
                        "failed": 8,
                        "pass_rate": "60.00%",
                        "answer_correctness": 0.667290301706683,
                        "source": "https://github.com/sparticleinc/ASEED/blob/main/evaluations/business_consulting/20240424-perplexity.json",
                        "source_csv": "https://github.com/sparticleinc/ASEED/blob/main/evaluations/business_consulting/20240424-perplexity.csv",
                        "evaluate_ai": "perplexity"
                    },
                    {
                        "total": 20,
                        "passed": 10,
                        "failed": 10,
                        "pass_rate": "50.00%",
                        "answer_correctness": 0.6324069653265152,
                        "source": "https://github.com/sparticleinc/ASEED/blob/main/evaluations/business_consulting/20240424-glarity_search.json",
                        "source_csv": "https://github.com/sparticleinc/ASEED/blob/main/evaluations/business_consulting/20240424-glarity_search.csv",
                        "evaluate_ai": "glarity_search"
                    },
                    {
                        "total": 20,
                        "passed": 11,
                        "failed": 9,
                        "pass_rate": "55.00%",
                        "answer_correctness": 0.6289624514648339,
                        "source": "https://github.com/sparticleinc/ASEED/blob/main/evaluations/business_consulting/20240424-metaso.json",
                        "source_csv": "https://github.com/sparticleinc/ASEED/blob/main/evaluations/business_consulting/20240424-metaso.csv",
                        "evaluate_ai": "metaso"
                    },
                    {
                        "total": 20,
                        "passed": 3,
                        "failed": 17,
                        "pass_rate": "15.00%",
                        "answer_correctness": 0.5813569803042006,
                        "source": "https://github.com/sparticleinc/ASEED/blob/main/evaluations/business_consulting/20240424-you.json",
                        "source_csv": "https://github.com/sparticleinc/ASEED/blob/main/evaluations/business_consulting/20240424-you.csv",
                        "evaluate_ai": "you"
                    },
                    {
                        "total": 20,
                        "passed": 8,
                        "failed": 12,
                        "pass_rate": "40.00%",
                        "answer_correctness": 0.594816959110364,
                        "source": "https://github.com/sparticleinc/ASEED/blob/main/evaluations/business_consulting/20240424-iask.json",
                        "source_csv": "https://github.com/sparticleinc/ASEED/blob/main/evaluations/business_consulting/20240424-iask.csv",
                        "evaluate_ai": "iask"
                    }
                ]
            }
        ],
        "total": 500,
        "passed": 296,
        "failed": 204,
        "pass_rate": "59.20%",
        "answer_correctness": 0.12419334631650387
    },
    {
        "date": "2024-04-22",
        "list": [
            {
                "scene": "technical_consulting",
                "total": 100,
                "passed": 25,
                "failed": 75,
                "pass_rate": "25.00%",
                "answer_correctness": 0.602574055795297,
                "list": [
                    {
                        "total": 20,
                        "passed": 7,
                        "failed": 13,
                        "pass_rate": "35.00%",
                        "answer_correctness": 0.5989955651500725,
                        "source": "https://github.com/sparticleinc/CRED/blob/main/evaluations/technical_consulting/20240422-perplexity.json",
                        "source_csv": "https://github.com/sparticleinc/CRED/blob/main/evaluations/technical_consulting/20240422-perplexity.csv",
                        "evaluate_ai": "perplexity"
                    },
                    {
                        "total": 20,
                        "passed": 7,
                        "failed": 13,
                        "pass_rate": "35.00%",
                        "answer_correctness": 0.6357217064687335,
                        "source": "https://github.com/sparticleinc/CRED/blob/main/evaluations/technical_consulting/20240422-glarity_search.json",
                        "source_csv": "https://github.com/sparticleinc/CRED/blob/main/evaluations/technical_consulting/20240422-glarity_search.csv",
                        "evaluate_ai": "glarity_search"
                    },
                    {
                        "total": 20,
                        "passed": 5,
                        "failed": 15,
                        "pass_rate": "25.00%",
                        "answer_correctness": 0.6233287879270992,
                        "source": "https://github.com/sparticleinc/CRED/blob/main/evaluations/technical_consulting/20240422-metaso.json",
                        "source_csv": "https://github.com/sparticleinc/CRED/blob/main/evaluations/technical_consulting/20240422-metaso.csv",
                        "evaluate_ai": "metaso"
                    },
                    {
                        "total": 20,
                        "passed": 3,
                        "failed": 17,
                        "pass_rate": "15.00%",
                        "answer_correctness": 0.5826333603528185,
                        "source": "https://github.com/sparticleinc/CRED/blob/main/evaluations/technical_consulting/20240422-you.json",
                        "source_csv": "https://github.com/sparticleinc/CRED/blob/main/evaluations/technical_consulting/20240422-you.csv",
                        "evaluate_ai": "you"
                    },
                    {
                        "total": 20,
                        "passed": 3,
                        "failed": 17,
                        "pass_rate": "15.00%",
                        "answer_correctness": 0.5721908590777611,
                        "source": "https://github.com/sparticleinc/CRED/blob/main/evaluations/technical_consulting/20240422-iask.json",
                        "source_csv": "https://github.com/sparticleinc/CRED/blob/main/evaluations/technical_consulting/20240422-iask.csv",
                        "evaluate_ai": "iask"
                    }
                ]
            },
            {
                "scene": "real_time_news",
                "total": 95,
                "passed": 25,
                "failed": 70,
                "pass_rate": "26.32%",
                "answer_correctness": 0.6224849711338132,
                "list": [
                    {
                        "total": 19,
                        "passed": 3,
                        "failed": 16,
                        "pass_rate": "15.79%",
                        "answer_correctness": 0.5957855397469977,
                        "source": "https://github.com/sparticleinc/CRED/blob/main/evaluations/real_time_news/20240422-perplexity.json",
                        "source_csv": "https://github.com/sparticleinc/CRED/blob/main/evaluations/real_time_news/20240422-perplexity.csv",
                        "evaluate_ai": "perplexity"
                    },
                    {
                        "total": 19,
                        "passed": 8,
                        "failed": 11,
                        "pass_rate": "42.11%",
                        "answer_correctness": 0.6661207688620167,
                        "source": "https://github.com/sparticleinc/CRED/blob/main/evaluations/real_time_news/20240422-glarity_search.json",
                        "source_csv": "https://github.com/sparticleinc/CRED/blob/main/evaluations/real_time_news/20240422-glarity_search.csv",
                        "evaluate_ai": "glarity_search"
                    },
                    {
                        "total": 19,
                        "passed": 3,
                        "failed": 16,
                        "pass_rate": "15.79%",
                        "answer_correctness": 0.5939334855800122,
                        "source": "https://github.com/sparticleinc/CRED/blob/main/evaluations/real_time_news/20240422-metaso.json",
                        "source_csv": "https://github.com/sparticleinc/CRED/blob/main/evaluations/real_time_news/20240422-metaso.csv",
                        "evaluate_ai": "metaso"
                    },
                    {
                        "total": 19,
                        "passed": 4,
                        "failed": 15,
                        "pass_rate": "21.05%",
                        "answer_correctness": 0.5856570316130244,
                        "source": "https://github.com/sparticleinc/CRED/blob/main/evaluations/real_time_news/20240422-you.json",
                        "source_csv": "https://github.com/sparticleinc/CRED/blob/main/evaluations/real_time_news/20240422-you.csv",
                        "evaluate_ai": "you"
                    },
                    {
                        "total": 19,
                        "passed": 7,
                        "failed": 12,
                        "pass_rate": "36.84%",
                        "answer_correctness": 0.670928029867015,
                        "source": "https://github.com/sparticleinc/CRED/blob/main/evaluations/real_time_news/20240422-iask.json",
                        "source_csv": "https://github.com/sparticleinc/CRED/blob/main/evaluations/real_time_news/20240422-iask.csv",
                        "evaluate_ai": "iask"
                    }
                ]
            },
            {
                "scene": "local_search",
                "total": 100,
                "passed": 51,
                "failed": 49,
                "pass_rate": "51.00%",
                "answer_correctness": 0.6522930209857102,
                "list": [
                    {
                        "total": 20,
                        "passed": 16,
                        "failed": 4,
                        "pass_rate": "80.00%",
                        "answer_correctness": 0.6932369205443997,
                        "source": "https://github.com/sparticleinc/CRED/blob/main/evaluations/local_search/20240422-perplexity.json",
                        "source_csv": "https://github.com/sparticleinc/CRED/blob/main/evaluations/local_search/20240422-perplexity.csv",
                        "evaluate_ai": "perplexity"
                    },
                    {
                        "total": 20,
                        "passed": 11,
                        "failed": 9,
                        "pass_rate": "55.00%",
                        "answer_correctness": 0.6773822222720673,
                        "source": "https://github.com/sparticleinc/CRED/blob/main/evaluations/local_search/20240422-glarity_search.json",
                        "source_csv": "https://github.com/sparticleinc/CRED/blob/main/evaluations/local_search/20240422-glarity_search.csv",
                        "evaluate_ai": "glarity_search"
                    },
                    {
                        "total": 20,
                        "passed": 13,
                        "failed": 7,
                        "pass_rate": "65.00%",
                        "answer_correctness": 0.6893186408077758,
                        "source": "https://github.com/sparticleinc/CRED/blob/main/evaluations/local_search/20240422-metaso.json",
                        "source_csv": "https://github.com/sparticleinc/CRED/blob/main/evaluations/local_search/20240422-metaso.csv",
                        "evaluate_ai": "metaso"
                    },
                    {
                        "total": 20,
                        "passed": 2,
                        "failed": 18,
                        "pass_rate": "10.00%",
                        "answer_correctness": 0.56466353326506,
                        "source": "https://github.com/sparticleinc/CRED/blob/main/evaluations/local_search/20240422-you.json",
                        "source_csv": "https://github.com/sparticleinc/CRED/blob/main/evaluations/local_search/20240422-you.csv",
                        "evaluate_ai": "you"
                    },
                    {
                        "total": 20,
                        "passed": 9,
                        "failed": 11,
                        "pass_rate": "45.00%",
                        "answer_correctness": 0.6368637880392481,
                        "source": "https://github.com/sparticleinc/CRED/blob/main/evaluations/local_search/20240422-iask.json",
                        "source_csv": "https://github.com/sparticleinc/CRED/blob/main/evaluations/local_search/20240422-iask.csv",
                        "evaluate_ai": "iask"
                    }
                ]
            },
            {
                "scene": "products_search",
                "total": 100,
                "passed": 50,
                "failed": 50,
                "pass_rate": "50.00%",
                "answer_correctness": 0.6663872606336334,
                "list": [
                    {
                        "total": 20,
                        "passed": 14,
                        "failed": 6,
                        "pass_rate": "70.00%",
                        "answer_correctness": 0.7277223081923802,
                        "source": "https://github.com/sparticleinc/CRED/blob/main/evaluations/products_search/20240422-perplexity.json",
                        "source_csv": "https://github.com/sparticleinc/CRED/blob/main/evaluations/products_search/20240422-perplexity.csv",
                        "evaluate_ai": "perplexity"
                    },
                    {
                        "total": 20,
                        "passed": 14,
                        "failed": 6,
                        "pass_rate": "70.00%",
                        "answer_correctness": 0.6972749115994583,
                        "source": "https://github.com/sparticleinc/CRED/blob/main/evaluations/products_search/20240422-glarity_search.json",
                        "source_csv": "https://github.com/sparticleinc/CRED/blob/main/evaluations/products_search/20240422-glarity_search.csv",
                        "evaluate_ai": "glarity_search"
                    },
                    {
                        "total": 20,
                        "passed": 9,
                        "failed": 11,
                        "pass_rate": "45.00%",
                        "answer_correctness": 0.6705742620487378,
                        "source": "https://github.com/sparticleinc/CRED/blob/main/evaluations/products_search/20240422-metaso.json",
                        "source_csv": "https://github.com/sparticleinc/CRED/blob/main/evaluations/products_search/20240422-metaso.csv",
                        "evaluate_ai": "metaso"
                    },
                    {
                        "total": 20,
                        "passed": 6,
                        "failed": 14,
                        "pass_rate": "30.00%",
                        "answer_correctness": 0.5838949469663925,
                        "source": "https://github.com/sparticleinc/CRED/blob/main/evaluations/products_search/20240422-you.json",
                        "source_csv": "https://github.com/sparticleinc/CRED/blob/main/evaluations/products_search/20240422-you.csv",
                        "evaluate_ai": "you"
                    },
                    {
                        "total": 20,
                        "passed": 7,
                        "failed": 13,
                        "pass_rate": "35.00%",
                        "answer_correctness": 0.6524698743611983,
                        "source": "https://github.com/sparticleinc/CRED/blob/main/evaluations/products_search/20240422-iask.json",
                        "source_csv": "https://github.com/sparticleinc/CRED/blob/main/evaluations/products_search/20240422-iask.csv",
                        "evaluate_ai": "iask"
                    }
                ]
            },
            {
                "scene": "business_consulting",
                "total": 100,
                "passed": 26,
                "failed": 74,
                "pass_rate": "26.00%",
                "answer_correctness": 0.6317252112661934,
                "list": [
                    {
                        "total": 20,
                        "passed": 7,
                        "failed": 13,
                        "pass_rate": "35.00%",
                        "answer_correctness": 0.6779688410393139,
                        "source": "https://github.com/sparticleinc/CRED/blob/main/evaluations/business_consulting/20240422-perplexity.json",
                        "source_csv": "https://github.com/sparticleinc/CRED/blob/main/evaluations/business_consulting/20240422-perplexity.csv",
                        "evaluate_ai": "perplexity"
                    },
                    {
                        "total": 20,
                        "passed": 6,
                        "failed": 14,
                        "pass_rate": "30.00%",
                        "answer_correctness": 0.6807864987899642,
                        "source": "https://github.com/sparticleinc/CRED/blob/main/evaluations/business_consulting/20240422-glarity_search.json",
                        "source_csv": "https://github.com/sparticleinc/CRED/blob/main/evaluations/business_consulting/20240422-glarity_search.csv",
                        "evaluate_ai": "glarity_search"
                    },
                    {
                        "total": 20,
                        "passed": 6,
                        "failed": 14,
                        "pass_rate": "30.00%",
                        "answer_correctness": 0.6302954194697623,
                        "source": "https://github.com/sparticleinc/CRED/blob/main/evaluations/business_consulting/20240422-metaso.json",
                        "source_csv": "https://github.com/sparticleinc/CRED/blob/main/evaluations/business_consulting/20240422-metaso.csv",
                        "evaluate_ai": "metaso"
                    },
                    {
                        "total": 20,
                        "passed": 1,
                        "failed": 19,
                        "pass_rate": "5.00%",
                        "answer_correctness": 0.5570960303148739,
                        "source": "https://github.com/sparticleinc/CRED/blob/main/evaluations/business_consulting/20240422-you.json",
                        "source_csv": "https://github.com/sparticleinc/CRED/blob/main/evaluations/business_consulting/20240422-you.csv",
                        "evaluate_ai": "you"
                    },
                    {
                        "total": 20,
                        "passed": 6,
                        "failed": 14,
                        "pass_rate": "30.00%",
                        "answer_correctness": 0.612479266717053,
                        "source": "https://github.com/sparticleinc/CRED/blob/main/evaluations/business_consulting/20240422-iask.json",
                        "source_csv": "https://github.com/sparticleinc/CRED/blob/main/evaluations/business_consulting/20240422-iask.csv",
                        "evaluate_ai": "iask"
                    }
                ]
            }
        ],
        "total": 495,
        "passed": 177,
        "failed": 318,
        "pass_rate": "35.76%",
        "answer_correctness": 0.6350929039629294
    },
    {
        "date": "2024-04-19",
        "list": [
            {
                "scene": "technical_consulting",
                "total": 105,
                "passed": 42,
                "failed": 63,
                "pass_rate": "40.00%",
                "answer_correctness": 0.584082183184764,
                "list": [
                    {
                        "total": 21,
                        "passed": 11,
                        "failed": 10,
                        "pass_rate": "52.38%",
                        "answer_correctness": 0.6330716947713477,
                        "source": "https://github.com/sparticleinc/CRED/blob/main/evaluations/technical_consulting/20240419-perplexity.json",
                        "evaluate_ai": "perplexity"
                    },
                    {
                        "total": 21,
                        "passed": 12,
                        "failed": 9,
                        "pass_rate": "57.14%",
                        "answer_correctness": 0.6254093015773811,
                        "source": "https://github.com/sparticleinc/CRED/blob/main/evaluations/technical_consulting/20240419-glarity_search.json",
                        "evaluate_ai": "glarity_search"
                    },
                    {
                        "total": 21,
                        "passed": 5,
                        "failed": 16,
                        "pass_rate": "23.81%",
                        "answer_correctness": 0.5632783832130972,
                        "source": "https://github.com/sparticleinc/CRED/blob/main/evaluations/technical_consulting/20240419-metaso.json",
                        "evaluate_ai": "metaso"
                    },
                    {
                        "total": 21,
                        "passed": 9,
                        "failed": 12,
                        "pass_rate": "42.86%",
                        "answer_correctness": 0.5849033901829215,
                        "source": "https://github.com/sparticleinc/CRED/blob/main/evaluations/technical_consulting/20240419-you.json",
                        "evaluate_ai": "you"
                    },
                    {
                        "total": 21,
                        "passed": 5,
                        "failed": 16,
                        "pass_rate": "23.81%",
                        "answer_correctness": 0.5137481461790718,
                        "source": "https://github.com/sparticleinc/CRED/blob/main/evaluations/technical_consulting/20240419-iask.json",
                        "evaluate_ai": "iask"
                    }
                ]
            },
            {
                "scene": "real_time_news",
                "total": 100,
                "passed": 27,
                "failed": 73,
                "pass_rate": "27.00%",
                "answer_correctness": 0.617115036005909,
                "list": [
                    {
                        "total": 20,
                        "passed": 7,
                        "failed": 13,
                        "pass_rate": "35.00%",
                        "answer_correctness": 0.6279670673764228,
                        "source": "https://github.com/sparticleinc/CRED/blob/main/evaluations/real_time_news/20240419-perplexity.json",
                        "evaluate_ai": "perplexity"
                    },
                    {
                        "total": 20,
                        "passed": 8,
                        "failed": 12,
                        "pass_rate": "40.00%",
                        "answer_correctness": 0.6565760035984721,
                        "source": "https://github.com/sparticleinc/CRED/blob/main/evaluations/real_time_news/20240419-glarity_search.json",
                        "evaluate_ai": "glarity_search"
                    },
                    {
                        "total": 20,
                        "passed": 1,
                        "failed": 19,
                        "pass_rate": "5.00%",
                        "answer_correctness": 0.5550978290406996,
                        "source": "https://github.com/sparticleinc/CRED/blob/main/evaluations/real_time_news/20240419-metaso.json",
                        "evaluate_ai": "metaso"
                    },
                    {
                        "total": 20,
                        "passed": 4,
                        "failed": 16,
                        "pass_rate": "20.00%",
                        "answer_correctness": 0.6198607518348095,
                        "source": "https://github.com/sparticleinc/CRED/blob/main/evaluations/real_time_news/20240419-you.json",
                        "evaluate_ai": "you"
                    },
                    {
                        "total": 20,
                        "passed": 7,
                        "failed": 13,
                        "pass_rate": "35.00%",
                        "answer_correctness": 0.6260735281791409,
                        "source": "https://github.com/sparticleinc/CRED/blob/main/evaluations/real_time_news/20240419-iask.json",
                        "evaluate_ai": "iask"
                    }
                ]
            },
            {
                "scene": "local_search",
                "total": 100,
                "passed": 51,
                "failed": 49,
                "pass_rate": "51.00%",
                "answer_correctness": 0.6471221294682077,
                "list": [
                    {
                        "total": 20,
                        "passed": 14,
                        "failed": 6,
                        "pass_rate": "70.00%",
                        "answer_correctness": 0.7068830719218595,
                        "source": "https://github.com/sparticleinc/CRED/blob/main/evaluations/local_search/20240419-perplexity.json",
                        "evaluate_ai": "perplexity"
                    },
                    {
                        "total": 20,
                        "passed": 13,
                        "failed": 7,
                        "pass_rate": "65.00%",
                        "answer_correctness": 0.6575839292983032,
                        "source": "https://github.com/sparticleinc/CRED/blob/main/evaluations/local_search/20240419-glarity_search.json",
                        "evaluate_ai": "glarity_search"
                    },
                    {
                        "total": 20,
                        "passed": 13,
                        "failed": 7,
                        "pass_rate": "65.00%",
                        "answer_correctness": 0.66357333053843,
                        "source": "https://github.com/sparticleinc/CRED/blob/main/evaluations/local_search/20240419-metaso.json",
                        "evaluate_ai": "metaso"
                    },
                    {
                        "total": 20,
                        "passed": 3,
                        "failed": 17,
                        "pass_rate": "15.00%",
                        "answer_correctness": 0.5726756753694012,
                        "source": "https://github.com/sparticleinc/CRED/blob/main/evaluations/local_search/20240419-you.json",
                        "evaluate_ai": "you"
                    },
                    {
                        "total": 20,
                        "passed": 8,
                        "failed": 12,
                        "pass_rate": "40.00%",
                        "answer_correctness": 0.6348946402130445,
                        "source": "https://github.com/sparticleinc/CRED/blob/main/evaluations/local_search/20240419-iask.json",
                        "evaluate_ai": "iask"
                    }
                ]
            },
            {
                "scene": "products_search",
                "total": 100,
                "passed": 54,
                "failed": 46,
                "pass_rate": "54.00%",
                "answer_correctness": 0.6521733573573155,
                "list": [
                    {
                        "total": 20,
                        "passed": 14,
                        "failed": 6,
                        "pass_rate": "70.00%",
                        "answer_correctness": 0.7117798175801493,
                        "source": "https://github.com/sparticleinc/CRED/blob/main/evaluations/products_search/20240419-perplexity.json",
                        "evaluate_ai": "perplexity"
                    },
                    {
                        "total": 20,
                        "passed": 16,
                        "failed": 4,
                        "pass_rate": "80.00%",
                        "answer_correctness": 0.6956239510846973,
                        "source": "https://github.com/sparticleinc/CRED/blob/main/evaluations/products_search/20240419-glarity_search.json",
                        "evaluate_ai": "glarity_search"
                    },
                    {
                        "total": 20,
                        "passed": 8,
                        "failed": 12,
                        "pass_rate": "40.00%",
                        "answer_correctness": 0.645266673241454,
                        "source": "https://github.com/sparticleinc/CRED/blob/main/evaluations/products_search/20240419-metaso.json",
                        "evaluate_ai": "metaso"
                    },
                    {
                        "total": 20,
                        "passed": 8,
                        "failed": 12,
                        "pass_rate": "40.00%",
                        "answer_correctness": 0.6141641343578209,
                        "source": "https://github.com/sparticleinc/CRED/blob/main/evaluations/products_search/20240419-you.json",
                        "evaluate_ai": "you"
                    },
                    {
                        "total": 20,
                        "passed": 8,
                        "failed": 12,
                        "pass_rate": "40.00%",
                        "answer_correctness": 0.5940322105224557,
                        "source": "https://github.com/sparticleinc/CRED/blob/main/evaluations/products_search/20240419-iask.json",
                        "evaluate_ai": "iask"
                    }
                ]
            },
            {
                "scene": "business_consulting",
                "total": 80,
                "passed": 32,
                "failed": 48,
                "pass_rate": "39.00%",
                "answer_correctness": 0.6365375414891405,
                "list": [
                    {
                        "total": 20,
                        "passed": 10,
                        "failed": 10,
                        "pass_rate": "50.00%",
                        "answer_correctness": 0.6601872013267639,
                        "source": "https://github.com/sparticleinc/CRED/blob/main/evaluations/business_consulting/20240419-perplexity.json",
                        "evaluate_ai": "perplexity"
                    },
                    {
                        "total": 20,
                        "passed": 12,
                        "failed": 8,
                        "pass_rate": "60.00%",
                        "answer_correctness": 0.6830701868699147,
                        "source": "https://github.com/sparticleinc/CRED/blob/main/evaluations/business_consulting/20240419-glarity_search.json",
                        "evaluate_ai": "glarity_search"
                    },
                    {
                        "total": 20,
                        "passed": 7,
                        "failed": 13,
                        "pass_rate": "35.00%",
                        "answer_correctness": 0.6312660448017569,
                        "source": "https://github.com/sparticleinc/CRED/blob/main/evaluations/business_consulting/20240419-metaso.json",
                        "evaluate_ai": "metaso"
                    },
                    {
                        "total": 20,
                        "passed": 3,
                        "failed": 17,
                        "pass_rate": "15.00%",
                        "answer_correctness": 0.5716267329581266,
                        "source": "https://github.com/sparticleinc/CRED/blob/main/evaluations/business_consulting/20240419-you.json",
                        "evaluate_ai": "you"
                    },
                    {
                        "total": 20,
                        "passed": 7,
                        "failed": 13,
                        "pass_rate": "35.00%",
                        "answer_correctness": 0.6061057636809093,
                        "source": "https://github.com/sparticleinc/CRED/blob/main/evaluations/business_consulting/20240419-iask.json",
                        "evaluate_ai": "iask"
                    }
                ]
            }
        ],
        "total": 485,
        "passed": 206,
        "failed": 279,
        "pass_rate": "42.47%",
        "answer_correctness": 0.6274060495010673
    }
]